<loadFolders>
  <v1.4>
    <li>/</li>
    <li>Common</li>
    <li>1.4</li>
    <!-- <li IfModActive="RedMattis.LamiasAndOtherSnakes">Mods/Snek</li> -->
    <li IfModActive="nals.facialanimation">1.4/Mods/FacialAnim</li>
    <li IfModActive="RedMattis.BigSmall">1.4/Mods/bs_races</li>
    <li IfModActive="erdelf.HumanoidAlienRaces">1.4/Mods/HAR</li>
  </v1.4>
  <v1.5>
    <li>/</li>
    <li>Common</li>
    <li>1.5</li>
    <!-- <li IfModActive="RedMattis.LamiasAndOtherSnakes">Mods/Snek</li> -->
    <li IfModActive="nals.facialanimation">1.5/Mods/FacialAnim</li>
    <li IfModActive="RedMattis.BigSmall">1.5/Mods/bs_races</li>
    <!-- <li IfModActive="erdelf.HumanoidAlienRaces">1.5/Mods/HAR</li> -->
  </v1.5>
  
</loadFolders>
